xstring/__init__.py
xstring/cmdline.py
xstring/config/__init__.py
xstring/config/settings.yml
xstring/editor/__init__.py
xstring/editor/base.py
xstring/log.py
xstring/manager/__init__.py
xstring/manager/base.py
xstring/manager/custom.py
xstring/manager/simple.py
xstring/parser/__init__.py
xstring/parser/base.py
xstring/schema.py
xstring-0.1.5.dist-info/LICENSE
xstring-0.1.5.dist-info/METADATA
xstring-0.1.5.dist-info/WHEEL
xstring-0.1.5.dist-info/entry_points.txt
xstring-0.1.5.dist-info/RECORD
