Metadata-Version: 2.1
Name: xstring
Version: 0.1.5
Summary: AI-powered automatic generation of documentation comments for classes, modules, and packages, including translation of existing comments and lazy customization of docstrings.
License: MIT
Author: yang chichi
Author-email: yangchichi@126.com
Requires-Python: >=3.10,<4.0
Classifier: License :: OSI Approved :: MIT License
Classifier: Operating System :: OS Independent
Classifier: Programming Language :: Python :: 3
Classifier: Programming Language :: Python :: 3.10
Classifier: Programming Language :: Python :: 3.11
Classifier: Programming Language :: Python :: 3.12
Requires-Dist: click (>=8.1.3,<9.0.0)
Requires-Dist: dynaconf (>=3.1.12,<4.0.0)
Requires-Dist: libcst (>=1.4.0,<2.0.0)
Requires-Dist: openai (>=1.35.7,<2.0.0)
Requires-Dist: rich (>=13.7.1,<14.0.0)
Requires-Dist: typer (>=0.12.3,<0.13.0)
